quick_scraping/__init__.py
quick_scraping/cli.py
quick_scraping/beautifulsoup_functions/__init__.py
quick_scraping/beautifulsoup_functions/examples.py
quick_scraping/beautifulsoup_functions/extractors.py
quick_scraping/beautifulsoup_functions/parser.py
quick_scraping/beautifulsoup_functions/utils.py
quick_scraping/common/__init__.py
quick_scraping/common/scraping_helper.py
quick_scraping/selenium_functions/__init__.py
quick_scraping/selenium_functions/alerts.py
quick_scraping/selenium_functions/config.py
quick_scraping/selenium_functions/elements.py
quick_scraping/selenium_functions/examples.py
quick_scraping/selenium_functions/frames.py
quick_scraping/selenium_functions/interactions.py
quick_scraping/selenium_functions/log_config.py
quick_scraping/selenium_functions/navigation.py
quick_scraping/selenium_functions/selenium_base.py
quick_scraping/selenium_functions/utils.py
quick_scraping-1.0.1.dist-info/licenses/LICENSE
quick_scraping-1.0.1.dist-info/METADATA
quick_scraping-1.0.1.dist-info/WHEEL
quick_scraping-1.0.1.dist-info/entry_points.txt
quick_scraping-1.0.1.dist-info/top_level.txt
quick_scraping-1.0.1.dist-info/RECORD
