Metadata-Version: 2.4
Name: quick-scraping
Version: 1.0.1
Summary: Toolkit para web scraping combinando Selenium e BeautifulSoup
Home-page: https://github.com/bruno-sardou/quick-scraping
Author: Bruno Sardou
Author-email: brunosardou@proton.me
Project-URL: Bug Tracker, https://github.com/bruno-sardou/quick-scraping/issues
Project-URL: Documentation, https://quick-scraping.readthedocs.io/
Project-URL: Source Code, https://github.com/bruno-sardou/quick-scraping
Keywords: web scraping,selenium,beautifulsoup,automation,html,parsing,extraction
Classifier: Programming Language :: Python :: 3
Classifier: Programming Language :: Python :: 3.7
Classifier: Programming Language :: Python :: 3.8
Classifier: Programming Language :: Python :: 3.9
Classifier: Programming Language :: Python :: 3.10
Classifier: License :: OSI Approved :: MIT License
Classifier: Operating System :: OS Independent
Classifier: Development Status :: 3 - Alpha
Classifier: Intended Audience :: Developers
Classifier: Topic :: Software Development :: Libraries :: Python Modules
Classifier: Topic :: Internet :: WWW/HTTP :: Browsers
Classifier: Topic :: Internet :: WWW/HTTP :: Dynamic Content
Requires-Python: >=3.7
License-File: LICENSE
Requires-Dist: beautifulsoup4>=4.9.0
Requires-Dist: selenium>=4.0.0
Requires-Dist: requests>=2.25.0
Requires-Dist: lxml>=4.6.0
Provides-Extra: dev
Requires-Dist: pytest>=6.0.0; extra == "dev"
Requires-Dist: black; extra == "dev"
Requires-Dist: flake8; extra == "dev"
Requires-Dist: mypy; extra == "dev"
Provides-Extra: docs
Requires-Dist: sphinx>=4.0.0; extra == "docs"
Requires-Dist: sphinx-rtd-theme; extra == "docs"
Dynamic: author
Dynamic: author-email
Dynamic: classifier
Dynamic: description
Dynamic: description-content-type
Dynamic: home-page
Dynamic: keywords
Dynamic: license-file
Dynamic: project-url
Dynamic: provides-extra
Dynamic: requires-dist
Dynamic: requires-python
Dynamic: summary
